LICENSE
MANIFEST.in
README.md
setup.py
django_sql_server_bcp/__init__.py
django_sql_server_bcp.egg-info/PKG-INFO
django_sql_server_bcp.egg-info/SOURCES.txt
django_sql_server_bcp.egg-info/dependency_links.txt
django_sql_server_bcp.egg-info/top_level.txt