Metadata-Version: 1.0
Name: django-sql-server-bcp
Version: 0.1.4
Summary: Utility for using mssql-tools BCP command with Django models
Home-page: https://github.com/ExoticObjects/ddjango-sql-server-bcp
Author: Exotic Objects LLC
Author-email: git@extc.co
License: MIT
Platform: UNKNOWN
